{
	"cmake" : 
	{
		"generator" : 
		{
			"multiConfig" : false,
			"name" : "Ninja"
		},
		"paths" : 
		{
			"cmake" : "/opt/homebrew/Cellar/cmake/4.2.1/bin/cmake",
			"cpack" : "/opt/homebrew/Cellar/cmake/4.2.1/bin/cpack",
			"ctest" : "/opt/homebrew/Cellar/cmake/4.2.1/bin/ctest",
			"root" : "/opt/homebrew/Cellar/cmake/4.2.1/share/cmake"
		},
		"version" : 
		{
			"isDirty" : false,
			"major" : 4,
			"minor" : 2,
			"patch" : 1,
			"string" : "4.2.1",
			"suffix" : ""
		}
	},
	"objects" : 
	[
		{
			"jsonFile" : "codemodel-v2-bbafa448aa7267388d18.json",
			"kind" : "codemodel",
			"version" : 
			{
				"major" : 2,
				"minor" : 9
			}
		},
		{
			"jsonFile" : "cache-v2-a994065236960cd16d89.json",
			"kind" : "cache",
			"version" : 
			{
				"major" : 2,
				"minor" : 0
			}
		},
		{
			"jsonFile" : "cmakeFiles-v1-d9ed2e039c9bda7adc0d.json",
			"kind" : "cmakeFiles",
			"version" : 
			{
				"major" : 1,
				"minor" : 1
			}
		}
	],
	"reply" : 
	{
		"cache-v2" : 
		{
			"jsonFile" : "cache-v2-a994065236960cd16d89.json",
			"kind" : "cache",
			"version" : 
			{
				"major" : 2,
				"minor" : 0
			}
		},
		"cmakeFiles-v1" : 
		{
			"jsonFile" : "cmakeFiles-v1-d9ed2e039c9bda7adc0d.json",
			"kind" : "cmakeFiles",
			"version" : 
			{
				"major" : 1,
				"minor" : 1
			}
		},
		"codemodel-v2" : 
		{
			"jsonFile" : "codemodel-v2-bbafa448aa7267388d18.json",
			"kind" : "codemodel",
			"version" : 
			{
				"major" : 2,
				"minor" : 9
			}
		}
	}
}
